COPYING
MANIFEST.in
Makefile
gpl.txt
lgpl.txt
requirements.txt
setup.py
chemlab/__init__.py
chemlab/ipython.py
chemlab/table.py
chemlab.egg-info/PKG-INFO
chemlab.egg-info/SOURCES.txt
chemlab.egg-info/dependency_links.txt
chemlab.egg-info/not-zip-safe
chemlab.egg-info/requires.txt
chemlab.egg-info/top_level.txt
chemlab/contrib/__init__.py
chemlab/contrib/gromacs.py
chemlab/core/__init__.py
chemlab/core/atom.py
chemlab/core/attributes.py
chemlab/core/base.py
chemlab/core/fields.py
chemlab/core/molecule.py
chemlab/core/random.py
chemlab/core/serialization.py
chemlab/core/system.py
chemlab/core/trajectory.py
chemlab/core/spacegroup/__init__.py
chemlab/core/spacegroup/__init__.pyc
chemlab/core/spacegroup/cell.py
chemlab/core/spacegroup/cell.pyc
chemlab/core/spacegroup/crystal.py
chemlab/core/spacegroup/crystal.pyc
chemlab/core/spacegroup/spacegroup.dat
chemlab/core/spacegroup/spacegroup.py
chemlab/core/spacegroup/spacegroup.pyc
chemlab/db/__init__.py
chemlab/db/base.py
chemlab/db/chemlabdb.py
chemlab/db/chemspiderdb.py
chemlab/db/cirdb.py
chemlab/db/lj.py
chemlab/db/local.py
chemlab/db/rcsbdb.py
chemlab/db/toxnetdb.py
chemlab/db/units.py
chemlab/db/utils.py
chemlab/db/localdb/__init__.py
chemlab/db/localdb/__init__.pyc
chemlab/db/localdb/data/__init__.py
chemlab/db/localdb/data/__init__.pyc
chemlab/db/localdb/data/covalent_radii.dat
chemlab/db/localdb/data/element.txt
chemlab/db/localdb/molecule/__init__.py
chemlab/db/localdb/molecule/__init__.pyc
chemlab/db/localdb/molecule/example.norbornene.json
chemlab/db/localdb/molecule/example.water.json
chemlab/db/localdb/molecule/gromacs.br-.json
chemlab/db/localdb/molecule/gromacs.cl-.json
chemlab/db/localdb/molecule/gromacs.li+.json
chemlab/db/localdb/molecule/gromacs.na+.json
chemlab/db/localdb/molecule/gromacs.spc.json
chemlab/db/localdb/molecule/gromacs.spce.json
chemlab/db/localdb/molecule/gromacs.urea.json
chemlab/graphics/__init__.py
chemlab/graphics/buffers.py
chemlab/graphics/camera.py
chemlab/graphics/colors.py
chemlab/graphics/pickers.py
chemlab/graphics/shaders.py
chemlab/graphics/textures.py
chemlab/graphics/transformations.py
chemlab/graphics/uis.py
chemlab/graphics/postprocessing/__init__.py
