Metadata-Version: 1.1
Name: chemlab
Version: 1.1
Summary: The python chemistry library you were waiting for
Home-page: https://chemlab.github.com/chemlab
Author: Gabriele Lanaro
Author-email: gabriele.lanaro@gmail.com
License: LGPL(no PyQt), GPL3(with PyQt)
Keywords: chemistry molecular_viewer
Platform: UNKNOWN
Classifier: Intended Audience :: Science/Research
Classifier: Topic :: Scientific/Engineering :: Chemistry
Classifier: Topic :: Scientific/Engineering :: Visualization
Classifier: Topic :: Scientific/Engineering :: Physics
Classifier: Topic :: Multimedia :: Graphics :: Viewers
Classifier: Programming Language :: Python :: 2.7
Classifier: Programming Language :: Python :: 3.3
